pythapi/__init__.py
pythapi/pythapi.py
pythapi-0.0.2.data/scripts/pythapi
pythapi-0.0.2.dist-info/LICENSE
pythapi-0.0.2.dist-info/METADATA
pythapi-0.0.2.dist-info/WHEEL
pythapi-0.0.2.dist-info/top_level.txt
pythapi-0.0.2.dist-info/RECORD
