Metadata-Version: 2.1
Name: pythapi
Version: 0.0.2
Summary: A micro framework for API calls
Home-page: https://github.com/geluyan/pythapi
Author: Andy Geluykens
Author-email: a.geluykens@gmail.com
License: UNKNOWN
Platform: UNKNOWN
Classifier: Programming Language :: Python :: 3
Classifier: License :: OSI Approved :: MIT License
Classifier: Operating System :: OS Independent
Requires-Dist: requests
